{
  "@context": [
    "https://www.w3.org/2018/credentials/v1",
    "https://w3id.org/security/suites/jws-2020/v1"
  ],
  "type": [
    "VerifiablePresentation"
  ],
  "proof": {
    "type": "JsonWebSignature2020",
    "proofPurpose": "authentication",
    "challenge": "123",
    "verificationMethod": "did:example:123#key-1",
    "created": "2021-12-06T14:50:48.565Z",
    "jws": "eyJhbGciOiJFUzI1NksiLCJjcml0IjpbImI2NCJdLCJiNjQiOmZhbHNlfQ..qNL92vc2Vo8nwtf6ZPp-AmEhXilosJ4Sle4AOu1ix9FzRrpZezbqPbrqtQz7se_4hKWj4OooBrErIqtwg6JUhQ"
  },
  "holder": "did:example:123"
}